ingaia_luigi_slack/__init__.py
ingaia_luigi_slack/api.py
ingaia_luigi_slack/events.py
ingaia_luigi_slack/slack_api.py
ingaia_luigi_slack-0.1.9.dist-info/LICENSE
ingaia_luigi_slack-0.1.9.dist-info/METADATA
ingaia_luigi_slack-0.1.9.dist-info/WHEEL
ingaia_luigi_slack-0.1.9.dist-info/top_level.txt
ingaia_luigi_slack-0.1.9.dist-info/RECORD
