Metadata-Version: 2.1
Name: ingaia-luigi-slack
Version: 0.1.9
Summary: Atualizado métodos api slack para notificação bot slack
Home-page: https://github.com/bonzanini
Author: Marco Bonzanini
Author-email: marco.bonzanini@gmail.com
License: MIT
Platform: UNKNOWN
Classifier: Environment :: Console
Classifier: Intended Audience :: Developers
Classifier: Intended Audience :: System Administrators
Classifier: Operating System :: OS Independent
Classifier: Programming Language :: Python
Classifier: License :: OSI Approved :: MIT License
Classifier: Programming Language :: Python :: 3.4
Classifier: Topic :: System :: Monitoring
License-File: LICENSE
Requires-Dist: luigi (>=1.3)
Requires-Dist: slackclient (<1.1,>=1.0)
